[
  {
    "name": "4.4",
    "releases": [
      {
        "name": "alpha.1",
        "release_date": "11 October 2024",
        "release_notes": "https://www.redotengine.org/news/release-4-4-alpha-1"
      }
    ]
  },
  {
    "name": "4.3",
    "releases": [
      {
        "name": "stable",
        "release_date": "25 November 2024",
        "release_notes": "https://www.redotengine.org/news/release-4-3-stable"
      },
      {
        "name": "rc.4",
        "release_date": "18 November 2024",
        "release_notes": "https://www.redotengine.org/news/release-4-3-rc-4"
      },
      {
        "name": "rc.3",
        "release_date": "13 November 2024",
        "release_notes": "https://www.redotengine.org/news/release-4-3-rc-3"
      },
      {
        "name": "rc.2",
        "release_date": "11 November 2024",
        "release_notes": "https://www.redotengine.org/news/release-4-3-rc-2"
      },
      {
        "name": "rc.1",
        "release_date": "7 November 2024",
        "release_notes": "https://www.redotengine.org/news/release-4-3-rc-1"
      },
      {
        "name": "beta.3",
        "release_date": "3 November 2024",
        "release_notes": "https://www.redotengine.org/news/release-4-3-beta-3"
      },
      {
        "name": "beta.2",
        "release_date": "31 October 2024",
        "release_notes": "https://www.redotengine.org/news/release-4-3-beta-2"
      },
      {
        "name": "beta.1",
        "release_date": "24 October 2024",
        "release_notes": "https://www.redotengine.org/news/release-4-3-beta-1"
      }
    ]
  }
]
